ecpz/__init__.py
ecpz/cli.py
ecpz/quine.cpp
ecpz/subprocess.h
ecpz/subprocess.hpp
ecpz-0.1.0.dist-info/LICENSE
ecpz-0.1.0.dist-info/METADATA
ecpz-0.1.0.dist-info/WHEEL
ecpz-0.1.0.dist-info/entry_points.txt
ecpz-0.1.0.dist-info/RECORD
