Metadata-Version: 2.3
Name: ecpz
Version: 0.1.0
Summary: Evaluate C++ using Python and Zig
License: MIT
Keywords: python,clang,c++
Author: Anton Pirogov
Author-email: apirogov@users.noreply.github.com
Requires-Python: >=3.10
Classifier: Intended Audience :: Developers
Classifier: Programming Language :: C++
Classifier: Topic :: Software Development :: Build Tools
Requires-Dist: dotenv (>=0.9.9,<0.10.0)
Requires-Dist: typer (>=0.15.2,<0.16.0)
Requires-Dist: zig-bin (>=0.14.0,<0.15.0)
Project-URL: Repository, https://github.com/apirogov/ecpz
